LICENSE
README.rst
setup.cfg
setup.py
fBb/__init__.py
fBb/fBb.py
fBb/fBb_2D.py
fBb/fBb_opti.py
fBb/simple_bridge.py
fBb/wind_fields.py
fBb.egg-info/PKG-INFO
fBb.egg-info/SOURCES.txt
fBb.egg-info/dependency_links.txt
fBb.egg-info/entry_points.txt
fBb.egg-info/requires.txt
fBb.egg-info/top_level.txt